plyvel-stubs/__init__.pyi
plyvel_stubs-0.0.1.dist-info/METADATA
plyvel_stubs-0.0.1.dist-info/WHEEL
plyvel_stubs-0.0.1.dist-info/licenses/LICENSE
plyvel_stubs-0.0.1.dist-info/RECORD
