Metadata-Version: 2.4
Name: plyvel-stubs
Version: 0.0.1
Summary: Type stubs for plyvel
Project-URL: Homepage, https://github.com/ysenarath/plyvel-stubs
Project-URL: Repository, https://github.com/ysenarath/plyvel-stubs
Author: ysenarath
License: MIT License
License-File: LICENSE
Keywords: leveldb,plyvel,stubs,typing
Classifier: Development Status :: 4 - Beta
Classifier: Intended Audience :: Developers
Classifier: License :: OSI Approved :: MIT License
Classifier: Programming Language :: Python :: 3
Classifier: Programming Language :: Python :: 3.8
Classifier: Programming Language :: Python :: 3.9
Classifier: Programming Language :: Python :: 3.10
Classifier: Programming Language :: Python :: 3.11
Classifier: Typing :: Stubs Only
